pathlib_abc/__init__.py
pathlib_abc/_fnmatch.py
pathlib_abc/_glob.py
pathlib_abc/_os.py
pathlib_abc-0.5.0.dist-info/METADATA
pathlib_abc-0.5.0.dist-info/WHEEL
pathlib_abc-0.5.0.dist-info/licenses/LICENSE.txt
pathlib_abc-0.5.0.dist-info/RECORD
