Metadata-Version: 2.4
Name: pathlib_abc
Version: 0.5.0
Summary: Backport of pathlib ABCs
Project-URL: Homepage, https://github.com/barneygale/pathlib-abc
Project-URL: Issues, https://github.com/barneygale/pathlib-abc/issues
Author-email: Barney Gale <barney.gale@gmail.com>
License: 1. This LICENSE AGREEMENT is between the Python Software Foundation
License-File: LICENSE.txt
Classifier: Intended Audience :: Developers
Classifier: License :: OSI Approved :: Python Software Foundation License
Classifier: Operating System :: OS Independent
Classifier: Programming Language :: Python :: 3
Requires-Python: >=3.9
